<?xml version="1.0" encoding="UTF-8"?>
<MetaDataObject xmlns="http://v8.1c.ru/8.3/MDClasses" xmlns:app="http://v8.1c.ru/8.2/managed-application/core" xmlns:cfg="http://v8.1c.ru/8.1/data/enterprise/current-config" xmlns:cmi="http://v8.1c.ru/8.2/managed-application/cmi" xmlns:ent="http://v8.1c.ru/8.1/data/enterprise" xmlns:lf="http://v8.1c.ru/8.2/managed-application/logform" xmlns:style="http://v8.1c.ru/8.1/data/ui/style" xmlns:sys="http://v8.1c.ru/8.1/data/ui/fonts/system" xmlns:v8="http://v8.1c.ru/8.1/data/core" xmlns:v8ui="http://v8.1c.ru/8.1/data/ui" xmlns:web="http://v8.1c.ru/8.1/data/ui/colors/web" xmlns:win="http://v8.1c.ru/8.1/data/ui/colors/windows" xmlns:xen="http://v8.1c.ru/8.3/xcf/enums" xmlns:xpr="http://v8.1c.ru/8.3/xcf/predef" xmlns:xr="http://v8.1c.ru/8.3/xcf/readable" xmlns:xs="http://www.w3.org/2001/XMLSchema" xmlns:xsi="http://www.w3.org/2001/XMLSchema-instance" version="2.18">
	<Constant uuid="f413985a-5ea4-4e49-b631-5b92b55cb3cb">
		<InternalInfo>
			<xr:GeneratedType name="ConstantManager.Порт" category="Manager">
				<xr:TypeId>89fadab3-9178-4e43-9a1e-93ee57522ce9</xr:TypeId>
				<xr:ValueId>0bb7c4eb-0294-4584-b20b-e4934e437eba</xr:ValueId>
			</xr:GeneratedType>
			<xr:GeneratedType name="ConstantValueManager.Порт" category="ValueManager">
				<xr:TypeId>8f769b17-0b75-4c3c-be69-2030dde32e32</xr:TypeId>
				<xr:ValueId>1ab084ba-71c1-44f5-972e-de46ce67d166</xr:ValueId>
			</xr:GeneratedType>
			<xr:GeneratedType name="ConstantValueKey.Порт" category="ValueKey">
				<xr:TypeId>2ddda9e1-90bb-40f2-889b-667c104f07b6</xr:TypeId>
				<xr:ValueId>72caf857-b531-4fef-9c78-36ad46dcf6ec</xr:ValueId>
			</xr:GeneratedType>
		</InternalInfo>
		<Properties>
			<Name>Порт</Name>
			<Synonym>
				<v8:item>
					<v8:lang>ru</v8:lang>
					<v8:content>Порт</v8:content>
				</v8:item>
			</Synonym>
			<Comment/>
			<Type>
				<v8:Type>xs:decimal</v8:Type>
				<v8:NumberQualifiers>
					<v8:Digits>10</v8:Digits>
					<v8:FractionDigits>0</v8:FractionDigits>
					<v8:AllowedSign>Nonnegative</v8:AllowedSign>
				</v8:NumberQualifiers>
			</Type>
			<UseStandardCommands>true</UseStandardCommands>
			<DefaultForm>CommonForm.RMQ</DefaultForm>
			<ExtendedPresentation/>
			<Explanation/>
			<PasswordMode>false</PasswordMode>
			<Format/>
			<EditFormat/>
			<ToolTip/>
			<MarkNegatives>false</MarkNegatives>
			<Mask/>
			<MultiLine>false</MultiLine>
			<ExtendedEdit>false</ExtendedEdit>
			<MinValue xsi:nil="true"/>
			<MaxValue xsi:nil="true"/>
			<FillChecking>DontCheck</FillChecking>
			<ChoiceFoldersAndItems>Items</ChoiceFoldersAndItems>
			<ChoiceParameterLinks/>
			<ChoiceParameters/>
			<QuickChoice>Auto</QuickChoice>
			<ChoiceForm/>
			<LinkByType/>
			<ChoiceHistoryOnInput>Auto</ChoiceHistoryOnInput>
			<DataLockControlMode>Managed</DataLockControlMode>
			<DataHistory>DontUse</DataHistory>
			<UpdateDataHistoryImmediatelyAfterWrite>false</UpdateDataHistoryImmediatelyAfterWrite>
			<ExecuteAfterWriteDataHistoryVersionProcessing>false</ExecuteAfterWriteDataHistoryVersionProcessing>
		</Properties>
	</Constant>
</MetaDataObject>